{
  "type": "LegendaryComponent",
  "output_item_id": 81645,
  "output_item_count": 1,
  "min_rating": 450,
  "time_to_craft_ms": 10000,
  "disciplines": [
    "Weaponsmith"
  ],
  "flags": [
    "LearnedFromItem"
  ],
  "ingredients": [
    {
      "item_id": 81961,
      "count": 30
    },
    {
      "item_id": 73296,
      "count": 1
    },
    {
      "item_id": 71574,
      "count": 1
    },
    {
      "item_id": 67832,
      "count": 1
    }
  ],
  "id": 12055,
  "chat_link": "[\u0026CRcvAAA\u003d]"
}