{
  "id": 12854,
  "type": "UpgradeComponent",
  "output_item_id": 24685,
  "output_item_count": 1,
  "time_to_craft_ms": 1000,
  "disciplines": [
    "Leatherworker",
    "Armorsmith",
    "Tailor"
  ],
  "min_rating": 400,
  "flags": [
    "LearnedFromItem"
  ],
  "ingredients": [
    {
      "item_id": 89271,
      "count": 1
    },
    {
      "item_id": 74090,
      "count": 1
    },
    {
      "item_id": 89103,
      "count": 1
    }
  ],
  "chat_link": "[\u0026CTYyAAA\u003d]",
  "guild_ingredients": []
}