{
  "id": 1685,
  "tier": 3,
  "order": 0,
  "name": "Purity of Body",
  "description": "Your Virtue skill 2 passive also regenerates endurance.",
  "slot": "Minor",
  "facts": [
    {
      "text": "Endurance Regeneration Increase",
      "type": "Percent",
      "icon": "https://render.guildwars2.com/file/9352ED3244417304995F26CB01AE76BB7E547052/156661.png",
      "percent": 15
    }
  ],
  "specialization": 49,
  "icon": "https://render.guildwars2.com/file/4393150B92392F32D10C3D551A363FE2C9400E27/1012413.png"
}