{
  "name": "Water Dragon Pauldrons",
  "type": "Armor",
  "flags": [
    "ShowInWardrobe"
  ],
  "restrictions": [],
  "rarity": "Basic",
  "id": 10916,
  "icon": "https://render.guildwars2.com/file/6A7E57A10DD5ED73340BE1C750A1646713795BC3/2719076.png",
  "details": {
    "type": "Shoulders",
    "weight_class": "Medium",
    "dye_slots": {
      "default": [
        {
          "color_id": -1,
          "material": "cloth"
        },
        {
          "color_id": -1,
          "material": "cloth"
        },
        {
          "color_id": -1,
          "material": "cloth"
        },
        {
          "color_id": -1,
          "material": "cloth"
        }
      ],
      "overrides": {}
    }
  }
}