{
  "name": "Draconic Coat",
  "type": "Armor",
  "flags": [
    "ShowInWardrobe"
  ],
  "restrictions": [],
  "rarity": "Basic",
  "id": 131,
  "icon": "https://render.guildwars2.com/file/E7FC2F5D02DBA0EE089BC615A5D2F1DFCFE6185F/61563.png",
  "details": {
    "type": "Coat",
    "weight_class": "Heavy",
    "dye_slots": {
      "default": [
        {
          "color_id": -1,
          "material": "metal"
        },
        {
          "color_id": -1,
          "material": "metal"
        },
        {
          "color_id": -1,
          "material": "leather"
        },
        null
      ],
      "overrides": {}
    }
  }
}