{
  "name": "Triumphant Hero\u0027s Wargreaves",
  "type": "Armor",
  "flags": [
    "ShowInWardrobe"
  ],
  "restrictions": [],
  "rarity": "Basic",
  "id": 6691,
  "icon": "https://render.guildwars2.com/file/9DF8D839C6DABFBC783CA1DFBEFE1DA957581F47/1424084.png",
  "details": {
    "type": "Boots",
    "weight_class": "Heavy",
    "dye_slots": {
      "default": [
        {
          "color_id": -1,
          "material": "metal"
        },
        {
          "color_id": -1,
          "material": "metal"
        },
        {
          "color_id": -1,
          "material": "leather"
        },
        {
          "color_id": -1,
          "material": "cloth"
        }
      ],
      "overrides": {
        "HumanFemale": [
          {
            "color_id": -1,
            "material": "metal"
          },
          {
            "color_id": -1,
            "material": "metal"
          },
          {
            "color_id": -1,
            "material": "leather"
          },
          null
        ],
        "HumanMale": [
          {
            "color_id": -1,
            "material": "metal"
          },
          {
            "color_id": -1,
            "material": "metal"
          },
          {
            "color_id": -1,
            "material": "metal"
          },
          {
            "color_id": -1,
            "material": "metal"
          }
        ],
        "NornFemale": [
          {
            "color_id": -1,
            "material": "metal"
          },
          {
            "color_id": -1,
            "material": "metal"
          },
          {
            "color_id": -1,
            "material": "leather"
          },
          null
        ],
        "NornMale": [
          {
            "color_id": -1,
            "material": "metal"
          },
          {
            "color_id": -1,
            "material": "metal"
          },
          {
            "color_id": -1,
            "material": "metal"
          },
          {
            "color_id": -1,
            "material": "metal"
          }
        ],
        "SylvariFemale": [
          {
            "color_id": -1,
            "material": "metal"
          },
          {
            "color_id": -1,
            "material": "metal"
          },
          {
            "color_id": -1,
            "material": "leather"
          },
          null
        ],
        "SylvariMale": [
          {
            "color_id": -1,
            "material": "metal"
          },
          {
            "color_id": -1,
            "material": "metal"
          },
          {
            "color_id": -1,
            "material": "metal"
          },
          {
            "color_id": -1,
            "material": "metal"
          }
        ]
      }
    }
  }
}