{
  "name": "White Mantle Elite Guard Mask",
  "description": "\u003cc\u003d@flavor\u003eThis mask is worn by elite members of Confessor Beetlestone\u0027s guard. Equipping does not guarantee acceptance in White Mantle cliques.\u003c/c\u003e",
  "type": "Armor",
  "flags": [
    "ShowInWardrobe"
  ],
  "restrictions": [],
  "rarity": "Basic",
  "id": 7073,
  "icon": "https://render.guildwars2.com/file/780A12759801FD3EE23077D19E6DF33CC3A3D755/1634560.png",
  "details": {
    "type": "Helm",
    "weight_class": "Light",
    "dye_slots": {
      "default": [
        {
          "color_id": -1,
          "material": "leather"
        },
        {
          "color_id": -1,
          "material": "leather"
        },
        {
          "color_id": -1,
          "material": "leather"
        },
        {
          "color_id": -1,
          "material": "leather"
        }
      ],
      "overrides": {}
    }
  }
}