{
  "name": "Warbeast Mask",
  "type": "Armor",
  "flags": [
    "ShowInWardrobe"
  ],
  "restrictions": [],
  "rarity": "Basic",
  "id": 7594,
  "icon": "https://render.guildwars2.com/file/06513C0CCB9AE980059358FCDE64323F12579CD6/1768400.png",
  "details": {
    "type": "Helm",
    "weight_class": "Medium",
    "dye_slots": {
      "default": [
        {
          "color_id": -1,
          "material": "metal"
        },
        {
          "color_id": -1,
          "material": "metal"
        },
        {
          "color_id": -1,
          "material": "cloth"
        },
        null
      ],
      "overrides": {}
    }
  }
}