{
  "name": "Salvaged Forged Gloves",
  "type": "Armor",
  "flags": [
    "ShowInWardrobe"
  ],
  "restrictions": [],
  "rarity": "Masterwork",
  "id": 7817,
  "icon": "https://render.guildwars2.com/file/5122665A96C374A223CAAA3E5F3475D81E910FAC/1876195.png",
  "details": {
    "type": "Gloves",
    "weight_class": "Light",
    "dye_slots": {
      "default": [
        {
          "color_id": -1,
          "material": "cloth"
        },
        {
          "color_id": -1,
          "material": "cloth"
        },
        {
          "color_id": -1,
          "material": "cloth"
        },
        {
          "color_id": -1,
          "material": "cloth"
        }
      ],
      "overrides": {}
    }
  }
}