{
  "name": "Mist Shard Pauldrons",
  "type": "Armor",
  "flags": [
    "ShowInWardrobe"
  ],
  "restrictions": [],
  "rarity": "Basic",
  "id": 8687,
  "icon": "https://render.guildwars2.com/file/BC0C68D14B69FAF32A947FBCEC07BEF200C15D27/2140905.png",
  "details": {
    "type": "Shoulders",
    "weight_class": "Heavy",
    "dye_slots": {
      "default": [
        {
          "color_id": -1,
          "material": "metal"
        },
        {
          "color_id": -1,
          "material": "metal"
        },
        {
          "color_id": -1,
          "material": "leather"
        },
        null
      ],
      "overrides": {}
    }
  }
}