{
  "name": "Valkyrie Tempered Scale Greaves",
  "description": "",
  "type": "Armor",
  "level": 55,
  "rarity": "Fine",
  "vendor_value": 57,
  "default_skin": 139,
  "game_types": [
    "Activity",
    "Wvw",
    "Dungeon",
    "Pve"
  ],
  "flags": [],
  "restrictions": [],
  "id": 10548,
  "chat_link": "[\u0026AgE0KQAA]",
  "icon": "https://render.guildwars2.com/file/39AD0FFC116EB9190E07E73446484DE8279151E7/61544.png",
  "details": {
    "type": "Boots",
    "weight_class": "Heavy",
    "defense": 82,
    "infusion_slots": [],
    "attribute_adjustment": 56.424,
    "infix_upgrade": {
      "id": 157,
      "attributes": [
        {
          "attribute": "Power",
          "modifier": 20
        },
        {
          "attribute": "Vitality",
          "modifier": 14
        },
        {
          "attribute": "CritDamage",
          "modifier": 14
        }
      ]
    }
  }
}