{
  "name": "Orange Coconut Cake",
  "type": "Consumable",
  "level": 55,
  "rarity": "Fine",
  "vendor_value": 26,
  "game_types": [
    "Wvw",
    "Dungeon",
    "Pve"
  ],
  "flags": [
    "NoSell"
  ],
  "restrictions": [],
  "id": 12388,
  "chat_link": "[\u0026AgFkMAAA]",
  "icon": "https://render.guildwars2.com/file/993E3B1603E2E4C877C041ACF1A6B965804701DF/339934.png",
  "details": {
    "type": "Food",
    "duration_ms": 1800000,
    "apply_count": 1,
    "name": "Nourishment",
    "icon": "https://render.guildwars2.com/file/779D3F0ABE5B46C09CFC57374DA8CC3A495F291C/436367.png",
    "description": "+10% Chill Duration\n+50 Power\n+10% Experience from Kills"
  }
}