{
  "name": "Vigorous Embroidered Wool Insignia",
  "description": "Used in the crafting of armor with +Power and +Vitality.",
  "type": "CraftingMaterial",
  "level": 0,
  "rarity": "Masterwork",
  "vendor_value": 17,
  "game_types": [
    "Activity",
    "Wvw",
    "Dungeon",
    "Pve"
  ],
  "flags": [
    "NoSalvage"
  ],
  "restrictions": [],
  "id": 19803,
  "chat_link": "[\u0026AgFbTQAA]",
  "icon": "https://render.guildwars2.com/file/9DEFFAF669D7BB264597F35EE4EB964A2A334117/220468.png"
}