{
  "name": "Shaman\u0027s Norn Focus of Corruption",
  "type": "Weapon",
  "level": 67,
  "rarity": "Rare",
  "vendor_value": 168,
  "default_skin": 5138,
  "game_types": [
    "Activity",
    "Wvw",
    "Dungeon",
    "Pve"
  ],
  "flags": [
    "SoulBindOnUse"
  ],
  "restrictions": [],
  "id": 25073,
  "chat_link": "[\u0026AgHxYQAA]",
  "icon": "https://render.guildwars2.com/file/7D6BF242BBB41774BF2DDC17BE0447C4C101D22A/575169.png",
  "details": {
    "type": "Focus",
    "damage_type": "Physical",
    "min_power": 589,
    "max_power": 625,
    "defense": 0,
    "infusion_slots": [],
    "attribute_adjustment": 234.216,
    "infix_upgrade": {
      "id": 153,
      "attributes": [
        {
          "attribute": "Vitality",
          "modifier": 82
        },
        {
          "attribute": "Healing",
          "modifier": 59
        },
        {
          "attribute": "ConditionDamage",
          "modifier": 59
        }
      ]
    },
    "suffix_item_id": 24577
  }
}