{
  "name": "Mending Shiverpeak Arquebus of the Hydromancer",
  "type": "Weapon",
  "level": 56,
  "rarity": "Masterwork",
  "vendor_value": 147,
  "default_skin": 5175,
  "game_types": [
    "Activity",
    "Wvw",
    "Dungeon",
    "Pve"
  ],
  "flags": [
    "SoulBindOnUse"
  ],
  "restrictions": [],
  "id": 25344,
  "chat_link": "[\u0026AgEAYwAA]",
  "icon": "https://render.guildwars2.com/file/1D625FA71BF2717F6AD5055DA5C40804221BC6A1/534285.png",
  "details": {
    "type": "Rifle",
    "damage_type": "Physical",
    "min_power": 527,
    "max_power": 645,
    "defense": 0,
    "infusion_slots": [],
    "attribute_adjustment": 336.192,
    "infix_upgrade": {
      "id": 147,
      "attributes": [
        {
          "attribute": "Vitality",
          "modifier": 84
        },
        {
          "attribute": "Healing",
          "modifier": 118
        }
      ]
    },
    "suffix_item_id": 24595
  }
}