{
  "name": "Strong Iron Mace",
  "description": "",
  "type": "Weapon",
  "level": 36,
  "rarity": "Fine",
  "vendor_value": 35,
  "default_skin": 3964,
  "game_types": [
    "Activity",
    "Wvw",
    "Dungeon",
    "Pve"
  ],
  "flags": [],
  "restrictions": [],
  "id": 26012,
  "chat_link": "[\u0026AgGcZQAA]",
  "icon": "https://render.guildwars2.com/file/415D42C379B3AE75721E59D76E5F170926C416C1/65228.png",
  "details": {
    "type": "Mace",
    "damage_type": "Physical",
    "min_power": 292,
    "max_power": 329,
    "defense": 0,
    "infusion_slots": [],
    "attribute_adjustment": 84.352,
    "infix_upgrade": {
      "id": 142,
      "attributes": [
        {
          "attribute": "Power",
          "modifier": 30
        },
        {
          "attribute": "Precision",
          "modifier": 21
        }
      ]
    }
  }
}