{
  "name": "Rampager\u0027s Iron Sword of Hobbling",
  "description": "",
  "type": "Weapon",
  "level": 78,
  "rarity": "Rare",
  "vendor_value": 192,
  "default_skin": 4062,
  "game_types": [
    "Activity",
    "Wvw",
    "Dungeon",
    "Pve"
  ],
  "flags": [
    "SoulBindOnUse"
  ],
  "restrictions": [],
  "id": 26515,
  "chat_link": "[\u0026AgGTZwAA]",
  "icon": "https://render.guildwars2.com/file/D10679012504F6AD5829D1DF9F36303FE2EB46B4/64343.png",
  "details": {
    "type": "Sword",
    "damage_type": "Physical",
    "min_power": 776,
    "max_power": 858,
    "defense": 0,
    "infusion_slots": [],
    "attribute_adjustment": 290.952,
    "infix_upgrade": {
      "id": 159,
      "attributes": [
        {
          "attribute": "Power",
          "modifier": 73
        },
        {
          "attribute": "Precision",
          "modifier": 102
        },
        {
          "attribute": "ConditionDamage",
          "modifier": 73
        }
      ]
    },
    "suffix_item_id": 24626
  }
}