{
  "name": "Berserker\u0027s Soft Wood Short Bow of Chilling",
  "description": "",
  "type": "Weapon",
  "level": 78,
  "rarity": "Exotic",
  "vendor_value": 384,
  "default_skin": 3906,
  "game_types": [
    "Activity",
    "Wvw",
    "Dungeon",
    "Pve"
  ],
  "flags": [
    "SoulBindOnUse"
  ],
  "restrictions": [],
  "id": 27790,
  "chat_link": "[\u0026AgGObAAA]",
  "icon": "https://render.guildwars2.com/file/0EFDC626FD430DA00CD9240C95EC6DF0500DB45E/67068.png",
  "details": {
    "type": "ShortBow",
    "damage_type": "Physical",
    "min_power": 876,
    "max_power": 969,
    "defense": 0,
    "infusion_slots": [],
    "attribute_adjustment": 658.72,
    "infix_upgrade": {
      "id": 161,
      "attributes": [
        {
          "attribute": "Power",
          "modifier": 231
        },
        {
          "attribute": "Precision",
          "modifier": 165
        },
        {
          "attribute": "CritDamage",
          "modifier": 165
        }
      ]
    },
    "suffix_item_id": 24630
  }
}