{
  "name": "Warden Axe",
  "description": "",
  "type": "Weapon",
  "level": 80,
  "rarity": "Rare",
  "vendor_value": 9000,
  "default_skin": 4260,
  "game_types": [
    "Activity",
    "Wvw",
    "Dungeon",
    "Pve"
  ],
  "flags": [
    "HideSuffix",
    "NoSalvage",
    "NoSell",
    "SoulbindOnAcquire",
    "SoulBindOnUse"
  ],
  "restrictions": [],
  "id": 29873,
  "chat_link": "[\u0026AgGxdAAA]",
  "icon": "https://render.guildwars2.com/file/64FFDE7251F4CD41FA1AB2CF76192818FEADE456/67845.png",
  "details": {
    "type": "Axe",
    "damage_type": "Physical",
    "min_power": 759,
    "max_power": 928,
    "defense": 0,
    "infusion_slots": [],
    "attribute_adjustment": 301.824,
    "infix_upgrade": {
      "id": 161,
      "attributes": [
        {
          "attribute": "Power",
          "modifier": 106
        },
        {
          "attribute": "Precision",
          "modifier": 75
        },
        {
          "attribute": "CritDamage",
          "modifier": 75
        }
      ]
    },
    "suffix_item_id": 24614
  }
}