{
  "name": "Mighty Apprentice Pants",
  "description": "",
  "type": "Armor",
  "level": 8,
  "rarity": "Basic",
  "vendor_value": 10,
  "default_skin": 3,
  "game_types": [
    "Activity",
    "Wvw",
    "Dungeon",
    "Pve"
  ],
  "flags": [],
  "restrictions": [],
  "id": 2994,
  "chat_link": "[\u0026AgGyCwAA]",
  "icon": "https://render.guildwars2.com/file/AAB41A903B03C7DEB833A8CC4E08CF0A02A67BD5/61404.png",
  "details": {
    "type": "Leggings",
    "weight_class": "Light",
    "defense": 17,
    "infusion_slots": [],
    "attribute_adjustment": 10.764,
    "infix_upgrade": {
      "id": 137,
      "attributes": [
        {
          "attribute": "Power",
          "modifier": 4
        }
      ]
    }
  }
}