{
  "name": "Tribal Talisman",
  "description": "",
  "type": "Weapon",
  "level": 80,
  "rarity": "Exotic",
  "vendor_value": 264,
  "default_skin": 4652,
  "game_types": [
    "Pvp",
    "PvpLobby"
  ],
  "flags": [
    "NoSell",
    "SoulbindOnAcquire",
    "SoulBindOnUse"
  ],
  "restrictions": [],
  "id": 31334,
  "chat_link": "[\u0026AgFmegAA]",
  "icon": "https://render.guildwars2.com/file/027833F7B4DB65057C590726A418BD3F59CEA7F2/63480.png",
  "details": {
    "type": "Focus",
    "damage_type": "Physical",
    "min_power": 832,
    "max_power": 883,
    "defense": 0,
    "infusion_slots": [],
    "attribute_adjustment": 341.44
  }
}