{
  "name": "Ravaging Glyphic Staff of Grawl Slaying",
  "type": "Weapon",
  "level": 32,
  "rarity": "Masterwork",
  "vendor_value": 96,
  "default_skin": 5237,
  "game_types": [
    "Activity",
    "Wvw",
    "Dungeon",
    "Pve"
  ],
  "flags": [
    "SoulBindOnUse"
  ],
  "restrictions": [],
  "id": 34588,
  "chat_link": "[\u0026AgEchwAA]",
  "icon": "https://render.guildwars2.com/file/009BF7054DD8F777207999EC76EA747801A4CA56/62802.png",
  "details": {
    "type": "Staff",
    "damage_type": "Physical",
    "min_power": 320,
    "max_power": 360,
    "defense": 0,
    "infusion_slots": [],
    "attribute_adjustment": 160.616,
    "infix_upgrade": {
      "id": 144,
      "attributes": [
        {
          "attribute": "Precision",
          "modifier": 40
        },
        {
          "attribute": "ConditionDamage",
          "modifier": 56
        }
      ]
    },
    "suffix_item_id": 24646
  }
}