{
  "name": "Ceremonial Dagger",
  "type": "Weapon",
  "level": 80,
  "rarity": "Exotic",
  "vendor_value": 264,
  "default_skin": 5107,
  "game_types": [
    "Activity",
    "Wvw",
    "Dungeon",
    "Pve"
  ],
  "flags": [
    "AccountBound",
    "SoulBindOnUse"
  ],
  "restrictions": [],
  "id": 38767,
  "chat_link": "[\u0026AgFvlwAA]",
  "icon": "https://render.guildwars2.com/file/636EFF76497216A515A10C473354B25029BC7EC7/534092.png",
  "details": {
    "type": "Dagger",
    "damage_type": "Physical",
    "min_power": 924,
    "max_power": 981,
    "defense": 0,
    "infusion_slots": [],
    "attribute_adjustment": 341.44,
    "stat_choices": [
      161,
      154,
      158
    ]
  }
}