{
  "name": "Soldier\u0027s Tribal Trident",
  "type": "Weapon",
  "level": 80,
  "rarity": "Exotic",
  "vendor_value": 396,
  "default_skin": 5127,
  "game_types": [
    "Activity",
    "Wvw",
    "Dungeon",
    "Pve"
  ],
  "flags": [
    "AccountBound",
    "SoulBindOnUse"
  ],
  "restrictions": [],
  "id": 38867,
  "chat_link": "[\u0026AgHTlwAA]",
  "icon": "https://render.guildwars2.com/file/52C4C1DD2A954317701A223EE8D7D5167FCDF7DA/780304.png",
  "details": {
    "type": "Trident",
    "damage_type": "Physical",
    "min_power": 905,
    "max_power": 1000,
    "defense": 0,
    "infusion_slots": [],
    "attribute_adjustment": 682.88,
    "infix_upgrade": {
      "id": 162,
      "attributes": [
        {
          "attribute": "Power",
          "modifier": 239
        },
        {
          "attribute": "Toughness",
          "modifier": 171
        },
        {
          "attribute": "Vitality",
          "modifier": 171
        }
      ]
    }
  }
}