{
  "name": "Deserter\u0027s Charr Alarm Clock",
  "type": "Weapon",
  "level": 55,
  "rarity": "Rare",
  "vendor_value": 150,
  "default_skin": 5149,
  "game_types": [
    "Activity",
    "Wvw",
    "Dungeon",
    "Pve"
  ],
  "flags": [
    "HideSuffix",
    "AccountBound",
    "NoMysticForge",
    "NoSell",
    "AccountBindOnUse"
  ],
  "restrictions": [],
  "id": 53710,
  "chat_link": "[\u0026AgHO0QAA]",
  "icon": "https://render.guildwars2.com/file/E40BED1EC22C9F5C5BAC0F432724A5CDE416A109/68175.png",
  "details": {
    "type": "Warhorn",
    "damage_type": "Physical",
    "min_power": 489,
    "max_power": 541,
    "defense": 0,
    "infusion_slots": [],
    "attribute_adjustment": 191.736,
    "infix_upgrade": {
      "id": 1014,
      "attributes": [
        {
          "attribute": "Toughness",
          "modifier": 48
        },
        {
          "attribute": "ConditionDamage",
          "modifier": 67
        }
      ]
    }
  }
}