{
  "name": "Handspar",
  "description": "A mysteriously light and well-balanced weapon that seems malleable to your wishes. Double-click to choose what form it should take.",
  "type": "Container",
  "level": 0,
  "rarity": "Fine",
  "vendor_value": 0,
  "game_types": [
    "Activity",
    "Wvw",
    "Dungeon",
    "Pve"
  ],
  "flags": [
    "AccountBound",
    "NoSalvage",
    "NoSell",
    "AccountBindOnUse"
  ],
  "restrictions": [],
  "id": 62095,
  "chat_link": "[\u0026AgGP8gAA]",
  "icon": "https://render.guildwars2.com/file/F0386CA4B7B424B01B54D7724D12A3DF09203E6D/66151.png",
  "details": {
    "type": "Default"
  }
}