{
  "name": "Recipe: Laranthir\u0027s Masque",
  "description": "A recipe to make an ascended light helm with Vigilant (+Power, +Toughness, +Concentration, and +Expertise) stats.",
  "type": "Consumable",
  "level": 0,
  "rarity": "Ascended",
  "vendor_value": 160,
  "game_types": [
    "PvpLobby",
    "Wvw",
    "Dungeon",
    "Pve"
  ],
  "flags": [
    "NoSalvage",
    "NoSell"
  ],
  "restrictions": [],
  "id": 74285,
  "chat_link": "[\u0026AgEtIgEA]",
  "icon": "https://render.guildwars2.com/file/AC1C3075784E0C4235BD9E22E1752D6B49D66F0F/849281.png",
  "details": {
    "type": "Unlock",
    "unlock_type": "CraftingRecipe",
    "recipe_id": 10480
  }
}