{
  "name": "Chest of the Garden",
  "description": "Contains the Essence of the Garden and recipes for completing Leaf of Kudzu.",
  "type": "Container",
  "level": 0,
  "rarity": "Exotic",
  "vendor_value": 264,
  "game_types": [
    "Wvw",
    "Dungeon",
    "Pve"
  ],
  "flags": [
    "AccountBound",
    "NoMysticForge",
    "NoSalvage",
    "DeleteWarning",
    "AccountBindOnUse"
  ],
  "restrictions": [],
  "id": 75046,
  "chat_link": "[\u0026AgEmJQEA]",
  "icon": "https://render.guildwars2.com/file/BEBBE67DAE30B2272F520ADD960D517FD1A59D68/1204754.png",
  "details": {
    "type": "Default"
  }
}