{
  "name": "Lesson: Extinct Creatures",
  "description": "The dangers of overeating.",
  "type": "Consumable",
  "level": 0,
  "rarity": "Rare",
  "vendor_value": 99,
  "game_types": [
    "Wvw",
    "Dungeon",
    "Pve"
  ],
  "flags": [
    "AccountBound",
    "NoMysticForge",
    "NoSalvage",
    "NoSell",
    "AccountBindOnUse"
  ],
  "restrictions": [],
  "id": 78470,
  "chat_link": "[\u0026AgGGMgEA]",
  "icon": "https://render.guildwars2.com/file/D35C6B2CF8403B4E150C3B626ECAF8A0590D0373/1423986.png",
  "details": {
    "type": "Immediate"
  }
}