{
  "name": "Grandmaster Weaponsmith\u0027s Mark",
  "description": "Can be used to purchase weaponsmith-created Ascended weapons from special merchants.",
  "type": "Trophy",
  "level": 80,
  "rarity": "Ascended",
  "vendor_value": 330,
  "game_types": [
    "Wvw",
    "Dungeon",
    "Pve"
  ],
  "flags": [
    "AccountBound",
    "NoSalvage",
    "NoSell",
    "AccountBindOnUse"
  ],
  "restrictions": [],
  "id": 80787,
  "chat_link": "[\u0026AgGTOwEA]",
  "icon": "https://render.guildwars2.com/file/015EAF57A9F3D90C2CBFC0EB4BADC1D64FDEDD41/1653625.png"
}