{
  "name": "Page of Spearmarshal Coat Recipes",
  "description": "Double-click to pick a recipe for Spearmarshal Coats. Can be learned by armorsmiths, leatherworkers, and tailors.\n\nPurchase these recipes from renown merchants in Elona after learning the base recipes from the story.",
  "type": "Container",
  "level": 0,
  "rarity": "Exotic",
  "vendor_value": 0,
  "game_types": [
    "PvpLobby",
    "Wvw",
    "Dungeon",
    "Pve"
  ],
  "flags": [
    "AccountBound",
    "NoSalvage",
    "AccountBindOnUse"
  ],
  "restrictions": [],
  "id": 83495,
  "chat_link": "[\u0026AgEnRgEA]",
  "icon": "https://render.guildwars2.com/file/D2C330A8D46973C70FF549A1D40A681FD4F1961A/1765998.png",
  "details": {
    "type": "Default"
  }
}