{
  "name": "Mini Sieran",
  "description": "Double-click to summon this mini to follow you around. Only one mini may be in use at a time.",
  "type": "MiniPet",
  "level": 0,
  "rarity": "Exotic",
  "vendor_value": 50,
  "game_types": [
    "PvpLobby",
    "Activity",
    "Wvw",
    "Dungeon",
    "Pve"
  ],
  "flags": [
    "NoSell",
    "DeleteWarning"
  ],
  "restrictions": [],
  "id": 85462,
  "chat_link": "[\u0026AgHWTQEA]",
  "icon": "https://render.guildwars2.com/file/99ECFFB60E1B72465B66EC1D90694E022C05740B/1861583.png",
  "details": {
    "minipet_id": 606
  }
}