{
  "name": "Metal Shipment",
  "description": "Open to receive an assortment of metal.",
  "type": "Container",
  "level": 0,
  "rarity": "Basic",
  "vendor_value": 32,
  "game_types": [
    "PvpLobby",
    "Wvw",
    "Dungeon",
    "Pve"
  ],
  "flags": [
    "AccountBound",
    "AccountBindOnUse"
  ],
  "restrictions": [],
  "id": 85990,
  "chat_link": "[\u0026AgHmTwEA]",
  "icon": "https://render.guildwars2.com/file/4B5E0734A136A1A62E1F149B07DBF113437DF403/1894767.png",
  "details": {
    "type": "Default"
  }
}