{
  "name": "Onion Seed Pouch",
  "description": "Collecting this seed unlocks the ability to plant this crop in your home\u0027s herb garden.",
  "type": "Consumable",
  "level": 0,
  "rarity": "Basic",
  "vendor_value": 0,
  "game_types": [
    "Wvw",
    "Dungeon",
    "Pve"
  ],
  "flags": [
    "AccountBound",
    "NoMysticForge",
    "NoSalvage",
    "AccountBindOnUse"
  ],
  "restrictions": [],
  "id": 86774,
  "chat_link": "[\u0026AgH2UgEA]",
  "icon": "https://render.guildwars2.com/file/694B6AC0292128A9E9CCA9A3BC4CE20442A97E3F/1925495.png",
  "details": {
    "type": "Generic"
  }
}