{
  "name": "Golem Swarm Potion",
  "description": "Double-click to transform into a swarm of miniature golems.",
  "type": "Consumable",
  "level": 0,
  "rarity": "Masterwork",
  "vendor_value": 0,
  "game_types": [
    "PvpLobby",
    "Wvw",
    "Dungeon",
    "Pve"
  ],
  "flags": [
    "AccountBound",
    "NoSalvage",
    "NoSell",
    "DeleteWarning",
    "AccountBindOnUse",
    "Tonic"
  ],
  "restrictions": [],
  "id": 87631,
  "chat_link": "[\u0026AgFPVgEA]",
  "icon": "https://render.guildwars2.com/file/D46466DF900E5A09CBC2F47F916880D933C52792/1998869.png",
  "details": {
    "type": "Food"
  }
}