{
  "name": "Potent Potion of Dredge Slaying",
  "type": "Consumable",
  "level": 70,
  "rarity": "Fine",
  "vendor_value": 2,
  "game_types": [
    "Wvw",
    "Dungeon",
    "Pve"
  ],
  "flags": [],
  "restrictions": [],
  "id": 8877,
  "chat_link": "[\u0026AgGtIgAA]",
  "icon": "https://render.guildwars2.com/file/0E560536F609C50677D0069907D744E95DD0D775/222812.png",
  "details": {
    "type": "Utility",
    "duration_ms": 1800000,
    "apply_count": 1,
    "name": "Enhancement",
    "icon": "https://render.guildwars2.com/file/64976F59BF060718C9109D36C27AD0F40F06BB32/436368.png",
    "description": "+9% Damage vs. Dredge\n-8% Damage from Dredge\n+10% Experience from Kills"
  }
}