{
  "name": "Royal Flame Scepter",
  "description": "\u003cc\u003d@flavor\u003eThe forges of the Mad Realm burn eternally over the year, awaiting the orders of their king.\u003c/c\u003e",
  "type": "Weapon",
  "level": 80,
  "rarity": "Exotic",
  "vendor_value": 264,
  "default_skin": 8973,
  "game_types": [
    "Activity",
    "Wvw",
    "Dungeon",
    "Pve"
  ],
  "flags": [
    "HideSuffix",
    "AccountBound",
    "NoSell",
    "AccountBindOnUse"
  ],
  "restrictions": [],
  "id": 92104,
  "chat_link": "[\u0026AgHIZwEA]",
  "icon": "https://render.guildwars2.com/file/F1165D9258F69FC402FCCA56E30E925171945F30/2212696.png",
  "details": {
    "type": "Scepter",
    "damage_type": "Physical",
    "min_power": 895,
    "max_power": 1010,
    "defense": 0,
    "infusion_slots": [],
    "attribute_adjustment": 341.44,
    "infix_upgrade": {
      "id": 1085,
      "attributes": [
        {
          "attribute": "Toughness",
          "modifier": 102
        },
        {
          "attribute": "Vitality",
          "modifier": 56
        },
        {
          "attribute": "ConditionDamage",
          "modifier": 102
        },
        {
          "attribute": "ConditionDuration",
          "modifier": 56
        }
      ]
    }
  }
}