{
  "name": "Fine Black Lion Dye Canister—Blue",
  "description": "Use to unlock exclusive Black Lion Chest blue dyes, or use to combine several canisters and upgrade their rarity.",
  "type": "Gizmo",
  "level": 0,
  "rarity": "Fine",
  "vendor_value": 0,
  "game_types": [
    "PvpLobby",
    "Wvw",
    "Dungeon",
    "Pve"
  ],
  "flags": [
    "NoSalvage",
    "NoSell",
    "DeleteWarning"
  ],
  "restrictions": [],
  "id": 92312,
  "chat_link": "[\u0026AgGYaAEA]",
  "icon": "https://render.guildwars2.com/file/F106560F2EBBF4C375B43FF0E13AE2945C3370D8/2220656.png",
  "details": {
    "type": "Default",
    "vendor_ids": [
      1811
    ]
  }
}