{
  "name": "Peppercorn and Veggie Flatbread",
  "type": "Gizmo",
  "level": 0,
  "rarity": "Basic",
  "vendor_value": 0,
  "game_types": [
    "Pve"
  ],
  "flags": [
    "AccountBound",
    "NoMysticForge",
    "NoSalvage",
    "NoSell",
    "AccountBindOnUse"
  ],
  "restrictions": [],
  "id": 92517,
  "chat_link": "[\u0026AgFlaQEA]",
  "icon": "https://render.guildwars2.com/file/C4FB4B7A4F99042798394CAA083157D04CD33128/2191028.png",
  "details": {
    "type": "Default",
    "guild_upgrade_id": 1129
  }
}