{
  "name": "Steel Warband Weapon Box",
  "description": "Double-click to open.\nThe weapons in this box unlock a journey to acquire multiple versions of their appearances.",
  "type": "Container",
  "level": 0,
  "rarity": "Rare",
  "vendor_value": 183,
  "game_types": [
    "PvpLobby",
    "Wvw",
    "Dungeon",
    "Pve"
  ],
  "flags": [
    "AccountBound",
    "AccountBindOnUse"
  ],
  "restrictions": [],
  "id": 93155,
  "chat_link": "[\u0026AgHjawEA]",
  "icon": "https://render.guildwars2.com/file/BD24B0FD915E43F2F57200D26576DC4B38D3F14C/2270297.png",
  "details": {
    "type": "Default"
  }
}