{
  "name": "Super Tree Branch",
  "description": "Deposit this decoration in the guild\u0027s decoration storage.",
  "type": "Consumable",
  "level": 0,
  "rarity": "Basic",
  "vendor_value": 0,
  "game_types": [
    "Activity",
    "Wvw",
    "Dungeon",
    "Pve"
  ],
  "flags": [
    "AccountBound",
    "NoMysticForge",
    "NoSalvage",
    "NoSell",
    "AccountBindOnUse"
  ],
  "restrictions": [],
  "id": 93317,
  "chat_link": "[\u0026AgGFbAEA]",
  "icon": "https://render.guildwars2.com/file/ADD316DC7B73DFDEFF0BA2E201F608249866CDB9/2281910.png",
  "details": {
    "type": "Generic",
    "guild_upgrade_id": 1146
  }
}