{
  "name": "Lorekeeper Dagger Skin",
  "description": "Double-click to apply this look to any other dagger.",
  "type": "Consumable",
  "level": 0,
  "rarity": "Rare",
  "vendor_value": 0,
  "game_types": [
    "PvpLobby",
    "Activity",
    "Wvw",
    "Dungeon",
    "Pve"
  ],
  "flags": [
    "NoMysticForge",
    "NoSalvage",
    "NoSell",
    "DeleteWarning"
  ],
  "restrictions": [],
  "id": 93971,
  "chat_link": "[\u0026AgETbwEA]",
  "icon": "https://render.guildwars2.com/file/C8BA673CB6200239FA69317164ABB3090291DF67/2328681.png",
  "details": {
    "type": "Transmutation",
    "skins": [
      9563
    ]
  }
}