{
  "name": "Etherbound Greatsword Skin",
  "description": "Double-click to apply this look to any other greatsword.",
  "type": "Consumable",
  "level": 0,
  "rarity": "Rare",
  "vendor_value": 0,
  "game_types": [
    "PvpLobby",
    "Activity",
    "Wvw",
    "Dungeon",
    "Pve"
  ],
  "flags": [
    "NoMysticForge",
    "NoSalvage",
    "NoSell",
    "DeleteWarning"
  ],
  "restrictions": [],
  "id": 94880,
  "chat_link": "[\u0026AgGgcgEA]",
  "icon": "https://render.guildwars2.com/file/41F9B018055809D642080AD9B1922A99342F5FCB/2418691.png",
  "details": {
    "type": "Transmutation",
    "skins": [
      9947
    ]
  }
}