{
  "name": "Endless Thundershrimp Tonic",
  "description": "Double-click to transform into a thundershrimp.\u003cbr\u003e\u003cbr\u003e\u003cc\u003d@flavor\u003e\"Still pretty big for a shrimp, if you ask me!\"\u003c/c\u003e",
  "type": "Gizmo",
  "level": 0,
  "rarity": "Exotic",
  "vendor_value": 104,
  "game_types": [
    "Wvw",
    "Dungeon",
    "Pve"
  ],
  "flags": [
    "NoSalvage",
    "NoSell",
    "Tonic"
  ],
  "restrictions": [],
  "id": 96710,
  "chat_link": "[\u0026AgHGeQEA]",
  "icon": "https://render.guildwars2.com/file/AFB753C31F206029EFDB3A281C20A4E128AD23DF/222638.png",
  "details": {
    "type": "Default"
  }
}