{
  "name": "Recipe: Knight\u0027s Intricate Linen Insignia",
  "description": "Double-click to learn a Rare Insignia Recipe.",
  "type": "Consumable",
  "level": 0,
  "rarity": "Rare",
  "vendor_value": 81,
  "game_types": [
    "Wvw",
    "Dungeon",
    "Pve"
  ],
  "flags": [
    "AccountBound",
    "NoSalvage",
    "NoSell",
    "AccountBindOnUse"
  ],
  "restrictions": [],
  "id": 9837,
  "chat_link": "[\u0026AgFtJgAA]",
  "icon": "https://render.guildwars2.com/file/3161A0FC2834BE23B5C55607F1CA7D932B982675/849387.png",
  "details": {
    "type": "Unlock",
    "unlock_type": "CraftingRecipe",
    "recipe_id": 245
  }
}