{
  "id": 2875,
  "icon": "https://render.guildwars2.com/file/B3DA5159BA6318466403EA14A47F0760633C48C5/630734.png",
  "name": "The Super Adventure",
  "description": "",
  "requirement": "Unlock all  Super Adventure weapon skins in your wardrobe.",
  "locked_text": "",
  "type": "ItemSet",
  "flags": [
    "IgnoreNearlyComplete",
    "Pvp",
    "RepairOnLogin",
    "Permanent"
  ],
  "bits": [
    {
      "type": "Skin",
      "id": 5288
    },
    {
      "type": "Skin",
      "id": 5324
    },
    {
      "type": "Skin",
      "id": 5274
    },
    {
      "type": "Skin",
      "id": 5308
    },
    {
      "type": "Skin",
      "id": 5325
    },
    {
      "type": "Skin",
      "id": 5284
    },
    {
      "type": "Skin",
      "id": 5292
    },
    {
      "type": "Skin",
      "id": 5279
    },
    {
      "type": "Skin",
      "id": 5301
    },
    {
      "type": "Skin",
      "id": 5299
    },
    {
      "type": "Skin",
      "id": 5311
    },
    {
      "type": "Skin",
      "id": 5258
    },
    {
      "type": "Skin",
      "id": 5334
    },
    {
      "type": "Skin",
      "id": 5344
    },
    {
      "type": "Skin",
      "id": 5251
    },
    {
      "type": "Skin",
      "id": 5261
    }
  ],
  "tiers": [
    {
      "count": 16,
      "points": 10
    }
  ],
  "rewards": [
    {
      "type": "Item",
      "id": 41886,
      "count": 50
    }
  ]
}