{
  "id": 3953,
  "icon": "https://render.guildwars2.com/file/3FB1AE472DF109D022146F26B0F420140BFC26FE/1824200.png",
  "name": "A Legend in the Flesh",
  "description": "",
  "requirement": "Unlock  Bounty Hunter\u0027s skins in your wardrobe by crafting or using the Trading Post. Recipes can be found by completing bounties or purchased from Elisa the Traveling Researcher in the Crystal Desert.",
  "locked_text": "",
  "type": "ItemSet",
  "flags": [
    "Pvp",
    "RepairOnLogin",
    "Permanent"
  ],
  "bits": [
    {
      "type": "Skin",
      "id": 7701
    },
    {
      "type": "Skin",
      "id": 7570
    },
    {
      "type": "Skin",
      "id": 7493
    },
    {
      "type": "Skin",
      "id": 7390
    },
    {
      "type": "Skin",
      "id": 7426
    },
    {
      "type": "Skin",
      "id": 7509
    },
    {
      "type": "Skin",
      "id": 7467
    },
    {
      "type": "Skin",
      "id": 7640
    },
    {
      "type": "Skin",
      "id": 7504
    },
    {
      "type": "Skin",
      "id": 7455
    },
    {
      "type": "Skin",
      "id": 7639
    },
    {
      "type": "Skin",
      "id": 7648
    },
    {
      "type": "Skin",
      "id": 7695
    },
    {
      "type": "Skin",
      "id": 7703
    },
    {
      "type": "Skin",
      "id": 7675
    },
    {
      "type": "Skin",
      "id": 7550
    },
    {
      "type": "Skin",
      "id": 7653
    },
    {
      "type": "Skin",
      "id": 7635
    }
  ],
  "tiers": [
    {
      "count": 1,
      "points": 1
    },
    {
      "count": 6,
      "points": 1
    },
    {
      "count": 12,
      "points": 1
    },
    {
      "count": 18,
      "points": 2
    }
  ],
  "rewards": [
    {
      "type": "Item",
      "id": 85624,
      "count": 1
    }
  ]
}