{
  "id": 4139,
  "name": "The Specimen Chamber",
  "description": "Inquest proposes. Commander disposes.",
  "requirement": "Defeat each champion simulacrum in the specimen chamber at least once.",
  "locked_text": "",
  "type": "Default",
  "flags": [
    "Permanent"
  ],
  "bits": [
    {
      "type": "Text",
      "text": "Simulacrum of Jord Ironfrost"
    },
    {
      "type": "Text",
      "text": "Simulacrum of Beyn, Scion of Thorns"
    },
    {
      "type": "Text",
      "text": "Simulacrum of Destroyer Crematus"
    },
    {
      "type": "Text",
      "text": "Simulacrum of Tlati, the Unchained"
    },
    {
      "type": "Text",
      "text": "Simulacrum of Varkesh, the Branded"
    },
    {
      "type": "Text",
      "text": "Simulacrum of Subject Beta"
    }
  ],
  "tiers": [
    {
      "count": 1,
      "points": 1
    },
    {
      "count": 2,
      "points": 1
    },
    {
      "count": 3,
      "points": 1
    },
    {
      "count": 4,
      "points": 1
    },
    {
      "count": 5,
      "points": 2
    },
    {
      "count": 6,
      "points": 3
    }
  ]
}