{
  "name": "The Great Hunt",
  "level": 1,
  "story": 2,
  "goals": [
    {
      "active": "Hunt down game animals and collect trophies.",
      "complete": "I hunted down prey for the Great Hunt, presented my trophies to the judges, and celebrated with my fellow hunters at the moot. Then I battled and defeated Issormir, the giant ice wurm. These victories earned me glory, and the right to call myself \"Slayer of Issormir.\" Soon every norn in Hoelbrak will be talking about me!"
    }
  ],
  "id": 154
}