{
  "name": "Magnet",
  "facts": [
    {
      "text": "Range",
      "type": "Range",
      "icon": "https://render.guildwars2.com/file/0AAB34BEB1C9F4A25EC612DDBEACF3E20B2810FA/156666.png",
      "value": 1200
    },
    {
      "text": "Recharge",
      "type": "Recharge",
      "icon": "https://render.guildwars2.com/file/D767B963D120F077C3B163A05DC05A7317D7DB70/156651.png",
      "value": 15
    },
    {
      "text": "Unblockable",
      "type": "Unblockable",
      "icon": "https://render.guildwars2.com/file/9352ED3244417304995F26CB01AE76BB7E547052/156661.png",
      "value": true
    }
  ],
  "description": "Pull your target to you.",
  "icon": "https://render.guildwars2.com/file/1244C52EA12E230336D30FA9CE14A4FEEBBDF0DB/103470.png",
  "type": "Bundle",
  "weapon_type": "None",
  "professions": [
    "Engineer"
  ],
  "slot": "Weapon_5",
  "flags": [],
  "id": 5996,
  "chat_link": "[\u0026BmwXAAA\u003d]"
}