{
  "name": "Signet of Resolve",
  "facts": [
    {
      "text": "Recharge",
      "type": "Recharge",
      "icon": "https://render.guildwars2.com/file/D767B963D120F077C3B163A05DC05A7317D7DB70/156651.png",
      "value": 30
    },
    {
      "text": "Healing",
      "type": "AttributeAdjust",
      "icon": "https://render.guildwars2.com/file/D4347C52157B040943051D7E09DEAD7AF63D4378/156662.png",
      "value": 8150,
      "target": "Healing"
    },
    {
      "text": "Interval",
      "type": "Time",
      "icon": "https://render.guildwars2.com/file/B75E91EB22E0DFCC1D08030204055946506D56F6/1770206.png",
      "duration": 5
    },
    {
      "text": "Passive Conditions Removed",
      "type": "Number",
      "icon": "https://render.guildwars2.com/file/9352ED3244417304995F26CB01AE76BB7E547052/156661.png",
      "value": 1
    },
    {
      "text": "Active Conditions Removed",
      "type": "Number",
      "icon": "https://render.guildwars2.com/file/9352ED3244417304995F26CB01AE76BB7E547052/156661.png",
      "value": 2
    }
  ],
  "description": "Signet Passive: Remove a condition from yourself every few seconds.\nSignet Active: Heal yourself and remove conditions.",
  "icon": "https://render.guildwars2.com/file/45904C2C787647E168F1A4B607471A32A8CB9609/103666.png",
  "type": "Heal",
  "weapon_type": "None",
  "professions": [
    "Guardian"
  ],
  "slot": "Heal",
  "flags": [],
  "id": 9158,
  "chat_link": "[\u0026BsYjAAA\u003d]",
  "categories": [
    "Signet"
  ],
  "traited_facts": [
    {
      "text": "Interval",
      "type": "Time",
      "icon": "https://render.guildwars2.com/file/B75E91EB22E0DFCC1D08030204055946506D56F6/1770206.png",
      "duration": 4,
      "requires_trait": 579,
      "overrides": 2
    }
  ]
}